sshsurf/__init__.py
sshsurf/client.py
sshsurf.py-0.0.1b0.dist-info/LICENSE
sshsurf.py-0.0.1b0.dist-info/METADATA
sshsurf.py-0.0.1b0.dist-info/WHEEL
sshsurf.py-0.0.1b0.dist-info/top_level.txt
sshsurf.py-0.0.1b0.dist-info/RECORD
