Metadata-Version: 2.1
Name: sshsurf.py
Version: 0.0.1b0
Summary: A wrapper for ssh.surf API
Home-page: https://github.com/OrdinaryEnder/sshsurf.py
Author: OrdinaryEnder
Author-email: endergaming1458@gmail.com
Classifier: Programming Language :: Python :: 3.8
Classifier: License :: OSI Approved :: Apache Software License
Classifier: Operating System :: OS Independent
Requires-Python: >=3.6
License-File: LICENSE
Requires-Dist: aiohttp
